htmldict/__init__.py
htmldict/annotated_dict.py
htmldict/core.py
htmldict/passkey.toml
htmldict/templates/card.html
htmldict/templates/default.css
htmldict/templates/detail.html
htmldict/templates/label.html
htmldict/test.html
htmldict/test_database/backups/2025-08-14/dummy_table.parquet
htmldict/test_database/backups/README.md
htmldict/test_database/changes.pkl
htmldict/test_database/config.toml
htmldict/test_database/test_database.db
htmldict-0.1.12.dist-info/LICENSE
htmldict-0.1.12.dist-info/METADATA
htmldict-0.1.12.dist-info/WHEEL
htmldict-0.1.12.dist-info/RECORD
