Metadata-Version: 2.3
Name: htmldict
Version: 0.1.12
Summary: Python dict objects with the ability to serve html
License: MIT
Author: Miles Copeland Luce
Requires-Python: >=3.13,<4.0
Classifier: License :: OSI Approved :: MIT License
Classifier: Programming Language :: Python :: 3
Classifier: Programming Language :: Python :: 3.13
Requires-Dist: flatten-dict (>=0.4.2,<0.5.0)
Requires-Dist: jinja2 (>=3.1.6,<4.0.0)
Requires-Dist: loguru (>=0.7.3,<0.8.0)
Requires-Dist: p2d2 (>=0.1.110,<0.2.0)
Requires-Dist: pandas (>=2.3.1,<3.0.0)
